flask_mailman_templates.py
flask_mailman_templates-0.1.2.dist-info/LICENSE
flask_mailman_templates-0.1.2.dist-info/METADATA
flask_mailman_templates-0.1.2.dist-info/WHEEL
flask_mailman_templates-0.1.2.dist-info/RECORD
