Metadata-Version: 2.1
Name: flask-mailman-templates
Version: 0.1.2
Summary: Templates for Flask-Mailman
Home-page: https://github.com/hyperflask/flask-mailman-templates
License: MIT
Author: Maxime Bouroumeau-Fuseau
Author-email: maxime.bouroumeau@gmail.com
Requires-Python: >=3.8,<4.0
Classifier: License :: OSI Approved :: MIT License
Classifier: Programming Language :: Python :: 3
Classifier: Programming Language :: Python :: 3.8
Classifier: Programming Language :: Python :: 3.9
Classifier: Programming Language :: Python :: 3.10
Classifier: Programming Language :: Python :: 3.11
Classifier: Programming Language :: Python :: 3.12
Requires-Dist: flask-mailman (>=1.1,<2.0)
Requires-Dist: html2text
Requires-Dist: jinja-frontmatter (>=0.1,<0.2)
Requires-Dist: markdown (>=3.6,<4.0)
Requires-Dist: mjml[css-inlining] (>=0.11,<0.12)
Requires-Dist: premailer (>=3.10,<4.0)
Project-URL: Repository, https://github.com/hyperflask/flask-mailman-templates
